rune_512/__init__.py
rune_512/__main__.py
rune_512/alphabet.py
rune_512/errors.py
rune_512/lib.py
rune_512-0.3.1.dist-info/licenses/LICENSE
rune_512-0.3.1.dist-info/METADATA
rune_512-0.3.1.dist-info/WHEEL
rune_512-0.3.1.dist-info/top_level.txt
rune_512-0.3.1.dist-info/RECORD
