Metadata-Version: 2.4
Name: rune-512
Version: 0.3.1
Summary: A Python implementation of the Rune-512 encoding and decoding algorithm.
Author-email: Lawrence Forman <me@merklejerk.com>
License-Expression: MIT
Project-URL: Homepage, https://github.com/merklejerk/rune-512
Project-URL: Repository, https://github.com/merklejerk/rune-512.git
Project-URL: Issues, https://github.com/merklejerk/rune-512/issues
Keywords: rune-512,encoding,decoding,base64,data encoding,binary encoding,codepoint encoding
Classifier: Programming Language :: Python :: 3
Classifier: Operating System :: OS Independent
Classifier: Intended Audience :: Developers
Classifier: Topic :: Software Development :: Libraries :: Python Modules
Requires-Python: >=3.9
License-File: LICENSE
Dynamic: license-file
